{"elapsed":"1.207","endpoint-url":"https://www.easthants.gov.uk/csv3-developer-transactions-csv-219-kb","entry-date":"2022-06-15T00:25:42.638148","request-headers":{"Accept":"*/*","Accept-Encoding":"gzip, deflate","Connection":"keep-alive","User-Agent":"DLUHC Digital Land"},"resource":"feec037dbe6771b352b0079f258233f654f148980ee6b1d461e81290dc5e7dd0","response-headers":{"Accept-Ranges":"bytes","Connection":"keep-alive","Content-Length":"224281","Content-Type":"text/csv","Date":"Wed, 15 Jun 2022 00:29:23 GMT","ETag":"\"b11bbb4fd98c0c59219a7fd83fcbdfa4\"","Last-Modified":"Mon, 13 Dec 2021 15:40:34 GMT","Server":"AmazonS3","Via":"1.1 5d4b6d16df71354239c0fbdbabb14154.cloudfront.net (CloudFront)","X-Amz-Cf-Id":"WRdYksetcGeVpnL-kqk3IIZVf91kLb1f6NKJSfLtWAnEjEOWSgupKw==","X-Amz-Cf-Pop":"DFW50-C1","X-Cache":"Miss from cloudfront"},"ssl-verify":true,"status":"200"}