{"elapsed":"1.582","endpoint-url":"https://www.havant.gov.uk/developer-contributions-csv-175-kb","entry-date":"2023-06-03T00:21:13.322230","request-headers":{"Accept":"*/*","Accept-Encoding":"gzip, deflate","Connection":"keep-alive","User-Agent":"DLUHC Digital Land"},"resource":"9c2b09492b644eda0af2e4961b7dd805ed46e1571b7df6d7899a9f7f85baab69","response-headers":{"Accept-Ranges":"bytes","Connection":"keep-alive","Content-Length":"179109","Content-Type":"text/csv","Date":"Sat, 03 Jun 2023 00:25:33 GMT","ETag":"\"8bb1ab016a46f9d3f369a229883f2324\"","Last-Modified":"Fri, 10 Dec 2021 15:28:17 GMT","Server":"AmazonS3","Via":"1.1 01a455b735347358143739c76de1ab1c.cloudfront.net (CloudFront)","X-Amz-Cf-Id":"ysyGUp8_0A6a98Sp8x69qVu2ojl9p3cGXNeGgr1oc-RcYHh3BVNw9g==","X-Amz-Cf-Pop":"SFO5-C1","X-Cache":"RefreshHit from cloudfront"},"ssl-verify":true,"status":"200"}