{"elapsed":"0.531","endpoint-url":"https://www.broxbourne.gov.uk/downloads/file/1304/developer-contributions","entry-date":"2023-08-23T00:20:14.180257","request-headers":{"Accept":"*/*","Accept-Encoding":"gzip, deflate","Connection":"keep-alive","Cookie":"PHPSESSID=RKNQn5wjS0HW3OF--5am3EpXEiMCz42Lazs2m0qvdZVVhqQ8p4bsYX64900tMHtk","User-Agent":"DLUHC Digital Land"},"response-headers":{"Cache-Control":"max-age=0, must-revalidate, private","Connection":"keep-alive","Content-Type":"text/html; charset=UTF-8","Date":"Wed, 23 Aug 2023 00:22:57 GMT","Expires":"Wed, 23 Aug 2023 00:22:57 GMT","Server":"Web Server","Transfer-Encoding":"chunked","X-Content-Type-Options":"nosniff","X-Frame-Options":"SAMEORIGIN","X-XSS-Protection":"1; mode=block"},"ssl-verify":true,"status":"404"}