{"elapsed":"1.165","endpoint-url":"https://www.havant.gov.uk/developer-agreements-csv-94-kb","entry-date":"2023-02-05T00:23:07.984018","request-headers":{"Accept":"*/*","Accept-Encoding":"gzip, deflate","Connection":"keep-alive","User-Agent":"DLUHC Digital Land"},"resource":"463cb51ccc0af8ebd05cc5f808fd0c8c580905ebd5b78adc7919fc3b694ffea3","response-headers":{"Accept-Ranges":"bytes","Connection":"keep-alive","Content-Length":"95662","Content-Type":"text/csv","Date":"Sun, 05 Feb 2023 00:26:01 GMT","ETag":"\"7027f47f52b0f27f1441037288a1f052\"","Last-Modified":"Fri, 10 Dec 2021 15:26:43 GMT","Server":"AmazonS3","Via":"1.1 1717f995f2ca7c5df4d0a972f90c1564.cloudfront.net (CloudFront)","X-Amz-Cf-Id":"YClICIW6mXS1Y7P93bhheppnFr7pZH8vfYkI4CUN2dHeVKz0dW66hA==","X-Amz-Cf-Pop":"IAD50-C2","X-Cache":"RefreshHit from cloudfront"},"ssl-verify":true,"status":"200"}