{"elapsed":"0.184","endpoint-url":"https://eryc.link/developertransactions  ","entry-date":"2021-05-19T01:05:30.955822","request-headers":{"Accept":"*/*","Accept-Encoding":"gzip, deflate","Connection":"keep-alive","User-Agent":"Digital Land"},"response-headers":{"Accept-Ranges":"bytes","Age":"1262","Connection":"keep-alive","Content-Length":"3633","Content-Type":"text/html","Date":"Wed, 19 May 2021 00:45:38 GMT","ETag":"\"5afd315a4cc6039b4dfd18cfa046304c\"","Last-Modified":"Fri, 02 Apr 2021 09:36:32 GMT","Server":"AmazonS3","Via":"1.1 603961b1b2dad8873023f00c2744bd6f.cloudfront.net (CloudFront)","X-Amz-Cf-Id":"NdhwIV2pL8dRMAJ5npSrawF8sy2aT593519PK_EEicMU921xY2J48A==","X-Amz-Cf-Pop":"IAD66-C2","X-Cache":"Hit from cloudfront"},"ssl-verify":true,"status":"200"}