{"elapsed":"0.375","endpoint-url":"https://cbccrmdata.blob.core.windows.net/noteattachment/CBC-Fees-and-charges-Developer-agreement-contributions-Developer%20Agreement%20Contributions_20201202.csv","entry-date":"2022-01-13T01:10:09.407988","request-headers":{"Accept":"*/*","Accept-Encoding":"gzip, deflate","Connection":"keep-alive","User-Agent":"DLUHC Digital Land"},"response-headers":{"Content-Length":"215","Content-Type":"application/xml","Date":"Thu, 13 Jan 2022 01:10:50 GMT","Server":"Windows-Azure-Blob/1.0 Microsoft-HTTPAPI/2.0","x-ms-request-id":"55bc4321-801e-0095-161a-084f6f000000","x-ms-version":"2009-09-19"},"ssl-verify":true,"status":"404"}