{"elapsed":"1.388","endpoint-url":"https://docs.tmbc.gov.uk/docs/S106/developer-agreement_20201209.csv","entry-date":"2024-02-24T00:20:15.811688","request-headers":{"Accept":"*/*","Accept-Encoding":"gzip, deflate","Connection":"keep-alive","User-Agent":"DLUHC Digital Land"},"response-headers":{"Content-Length":"1245","Content-Type":"text/html","Date":"Sat, 24 Feb 2024 00:21:02 GMT","Server":"Microsoft-IIS/8.5","Strict-Transport-Security":"max-age=31536000","X-Powered-By":"ASP.NET"},"ssl-verify":true,"status":"404"}