{"elapsed":"0.447","endpoint-url":"https://www.southhams.gov.uk/developer-agreement-contribution","entry-date":"2024-02-10T00:20:14.049783","request-headers":{"Accept":"*/*","Accept-Encoding":"gzip, deflate","Connection":"keep-alive","User-Agent":"DLUHC Digital Land"},"resource":"c38577531d5a9ad9213b4e19903eb8e51ebf3903b04490652480bf13fcecc470","response-headers":{"Accept-Ranges":"bytes","Age":"102","Connection":"keep-alive","Content-Length":"5373","Content-Type":"application/octet-stream","Date":"Sat, 10 Feb 2024 00:21:08 GMT","ETag":"\"65844056-14fd\"","Last-Modified":"Thu, 21 Dec 2023 13:40:38 GMT","Server":"nginx","Via":"1.1 0501dadffc52b06a0cf6aadc57586acc.cloudfront.net (CloudFront)","X-Amz-Cf-Id":"3pWpXOty2NF22_yWPwpGePU5u0ymB3b-qzcxHQd-8nGryOaubhWUIQ==","X-Amz-Cf-Pop":"IAD89-P1","X-Cache":"Hit from cloudfront","X-Content-Type-Options":"nosniff"},"ssl-verify":true,"status":"200"}