{"elapsed":"0.764","endpoint-url":"https://www.islington.gov.uk/developer-agreement","entry-date":"2021-12-28T01:04:55.342712","request-headers":{"Accept":"*/*","Accept-Encoding":"gzip, deflate","Connection":"keep-alive","Cookie":"{05DAD3A3-7484-411E-9233-D9F052219632}-CurrentCycle=Cycle=1; ARRAffinity=d84cc804bfb2e8ac483350d9629f929be6ad951a81a3393b3b37fadae86f7c85; ARRAffinitySameSite=d84cc804bfb2e8ac483350d9629f929be6ad951a81a3393b3b37fadae86f7c85","User-Agent":"DLUHC Digital Land"},"resource":"969c98b4e9472b0e945e96b62d03b1e99d137b57840140b1a745fbf9a8b74647","response-headers":{"Cache-Control":"private, max-age=604800","Content-Length":"12947","Content-Type":"text/csv","Date":"Tue, 28 Dec 2021 01:05:17 GMT","Expires":"Tue, 04 Jan 2022 01:05:18 GMT","Last-Modified":"Wed, 17 Nov 2021 15:22:36 GMT","Server":"Microsoft-IIS/10.0","X-UA-Compatible":"IE=edge"},"ssl-verify":true,"status":"200"}