{"elapsed":"1.515","endpoint-url":"https://www.carlisle.gov.uk/Portals/24/Documents/Evidence_Base/IFS/developer-agreement-transactions20201230.csv","entry-date":"2023-05-30T00:21:30.452802","request-headers":{"Accept":"*/*","Accept-Encoding":"gzip, deflate","Connection":"keep-alive","User-Agent":"DLUHC Digital Land"},"resource":"1ac5852856bd9ed721caba9ed88a27ca6e65776f2ee82b7e717e6d348ad3f9a8","response-headers":{"Accept-Ranges":"bytes","CF-Cache-Status":"MISS","CF-RAY":"7cf2d54c5d18e9c1-DFW","Cache-Control":"max-age=691200","Connection":"keep-alive","Content-Length":"2151","Content-Type":"application/octet-stream","Date":"Tue, 30 May 2023 00:24:17 GMT","NEL":"{\"success_fraction\":0,\"report_to\":\"cf-nel\",\"max_age\":604800}","Report-To":"{\"endpoints\":[{\"url\":\"https:\\/\\/a.nel.cloudflare.com\\/report\\/v3?s=B5wehLYtnRa73a9Ot8DqK5sVnv1gzE865ZHhzWgDArIMfTMV%2FAl4Q1%2Ba9egJkeqsXUSqDYSpWcdXnDbsI4y3bWFSXhim5az2GPOMR%2FL9a9lVxtnbSTZ5cOSwlmTrHFeSsZNcLLI%3D\"}],\"group\":\"cf-nel\",\"max_age\":604800}","Server":"cloudflare","Vary":"Accept-Encoding","etag":"\"df75269030e8d61:0\"","last-modified":"Mon, 11 Jan 2021 15:43:52 GMT","strict-transport-security":"max-age=63072000","x-content-type-options":"nosniff","x-frame-options":"SAMEORIGIN","x-ua-compatible":"IE=edge","x-xss-protection":"1; mode=block"},"ssl-verify":true,"status":"200"}