{"elapsed":"0.505","endpoint-url":"https://epsom-ewell.gov.uk/sites/default/files/documents/residents/planning/planning-policy/community-infrastructure-levy-cil/developer-agreement.csv","entry-date":"2023-12-18T00:21:19.108280","request-headers":{"Accept":"*/*","Accept-Encoding":"gzip, deflate","Connection":"keep-alive","User-Agent":"DLUHC Digital Land"},"resource":"3b2b2840f5d22b045794f23e9b9c4bda1571217fb5aad71e22a4f44a0ff2d20b","response-headers":{"Accept-Ranges":"bytes","Age":"0","Connection":"keep-alive","Content-Length":"2684","Content-Type":"text/csv","Date":"Mon, 18 Dec 2023 00:21:27 GMT","Etag":"\"62b99a1b-a7c\"","Last-Modified":"Mon, 27 Jun 2022 11:52:59 GMT","Server":"nginx","Strict-Transport-Security":"max-age=300","Via":"1.1 varnish, 1.1 varnish","X-Cache":"MISS, MISS","X-Cache-Hits":"0, 0","X-Pantheon-Styx-Hostname":"styx-fe1fe2-c-6d496dcddd-lj78f","X-Served-By":"cache-ams12725-AMS, cache-iad-kcgs7200088-IAD","X-Styx-Req-Id":"62a02b1e-9d3b-11ee-a741-925f8bc92740","X-Timer":"S1702858888.789298,VS0,VE202"},"ssl-verify":true,"status":"200"}