{"elapsed":"0.949","endpoint-url":"https://southhams.gov.uk/developer-agreement-contribution","entry-date":"2024-01-12T00:20:47.733746","request-headers":{"Accept":"*/*","Accept-Encoding":"gzip, deflate","Connection":"keep-alive","User-Agent":"DLUHC Digital Land"},"resource":"c38577531d5a9ad9213b4e19903eb8e51ebf3903b04490652480bf13fcecc470","response-headers":{"Accept-Ranges":"bytes","Connection":"keep-alive","Content-Length":"5373","Content-Type":"application/octet-stream","Date":"Fri, 12 Jan 2024 00:21:53 GMT","ETag":"\"65844056-14fd\"","Last-Modified":"Thu, 21 Dec 2023 13:40:38 GMT","Server":"nginx","Via":"1.1 224ff291656c355124a517edfd057cea.cloudfront.net (CloudFront)","X-Amz-Cf-Id":"g89n2-19J-cwa9brpxe7fqHwh6BsCs_CrQSmVcN3M3pOqiC_gMyc_Q==","X-Amz-Cf-Pop":"ORD56-P6","X-Cache":"Miss from cloudfront","X-Content-Type-Options":"nosniff"},"ssl-verify":true,"status":"200"}