{"elapsed":"1.365","endpoint-url":"https://westdevon.gov.uk/developer-agreement-transaction","entry-date":"2023-10-08T00:20:22.604510","request-headers":{"Accept":"*/*","Accept-Encoding":"gzip, deflate","Connection":"keep-alive","User-Agent":"DLUHC Digital Land"},"resource":"2c86a4234364632ee79a2af6a72c5657be34bc0859c8102621b19961dfa1983f","response-headers":{"Accept-Ranges":"bytes","CF-Cache-Status":"MISS","CF-RAY":"812a39f789130939-IAD","Cache-Control":"max-age=14400","Connection":"keep-alive","Content-Length":"13040","Content-Type":"application/vnd.openxmlformats-officedocument.spreadsheetml.sheet","Date":"Sun, 08 Oct 2023 00:21:54 GMT","ETag":"\"647f3ebf-32f0\"","Last-Modified":"Tue, 06 Jun 2023 14:12:15 GMT","NEL":"{\"success_fraction\":0,\"report_to\":\"cf-nel\",\"max_age\":604800}","Report-To":"{\"endpoints\":[{\"url\":\"https:\\/\\/a.nel.cloudflare.com\\/report\\/v3?s=KMzpyllaNXo6saMkzhNVgCIZc0ZREp9IbIa70t1M6PMLeQRZ4ZXslA%2FiSA8mEzKItRCe9PNKfAOO3%2FwZNExyhk1D8iZuptMvLaDICKGqvEuxDmpPXJo3j%2F%2FtVwe1DrWzA40YdS1XaQ%3D%3D\"}],\"group\":\"cf-nel\",\"max_age\":604800}","Server":"cloudflare","Vary":"Accept-Encoding","X-Content-Type-Options":"nosniff","alt-svc":"h3=\":443\"; ma=86400"},"ssl-verify":true,"status":"200"}