{"elapsed":"2.576","endpoint-url":"https://westdevon.gov.uk/developer-agreement","entry-date":"2023-11-24T00:19:23.275743","request-headers":{"Accept":"*/*","Accept-Encoding":"gzip, deflate","Connection":"keep-alive","User-Agent":"DLUHC Digital Land"},"resource":"29e2d900019b7e4961196ab0c4800a09425d73d5238ed7a8ceaa181e50e00903","response-headers":{"Accept-Ranges":"bytes","Connection":"keep-alive","Content-Length":"13693","Content-Type":"application/vnd.openxmlformats-officedocument.spreadsheetml.sheet","Date":"Fri, 24 Nov 2023 00:20:14 GMT","ETag":"\"647f3e9c-357d\"","Last-Modified":"Tue, 06 Jun 2023 14:11:40 GMT","Server":"nginx","Via":"1.1 75109f22d44404e68915a641fc09f102.cloudfront.net (CloudFront)","X-Amz-Cf-Id":"1_Lf00u9SSU9_ga5r_UQHUUB_Ix4M8YMjsFdPez53ru565p3_8-l5w==","X-Amz-Cf-Pop":"SFO53-P1","X-Cache":"Miss from cloudfront","X-Content-Type-Options":"nosniff"},"ssl-verify":true,"status":"200"}