{"bytes":44802,"elapsed":"4.274","endpoint-url":"https://www.iow.gov.uk/PlanningObligations/Download.ashx?type=Extract&extract=Agreements","entry-date":"2021-12-22T01:06:53.104061","request-headers":{"Accept":"*/*","Accept-Encoding":"gzip, deflate","Connection":"keep-alive","User-Agent":"DLUHC Digital Land"},"resource":"4d5ecaafafaed8b6da9c47fff2ed15941b4b749b1eb23bbb93cce8b24aa898d6","response-headers":{"Cache-Control":"private","Content-Disposition":"attachment; filename=developer-agreement_20211222.csv","Content-Length":"44802","Content-Security-Policy":"frame-ancestors https://*.iow.gov.uk","Content-Type":"text/csv","Date":"Wed, 22 Dec 2021 01:06:44 GMT","Server":"Microsoft-IIS/10.0","X-Frame-Options":"allow-from https://crm.iow.gov.uk"},"ssl-verify":true,"status":"200"}