{"elapsed":"0.487","endpoint-url":"https://www.eastcambs.gov.uk/sites/default/files/developer-agreement-contribution_2020-10-12.csv","entry-date":"2023-10-26T00:20:51.277044","request-headers":{"Accept":"*/*","Accept-Encoding":"gzip, deflate","Connection":"keep-alive","User-Agent":"DLUHC Digital Land"},"resource":"e15f264e573705c31eaec00f00ea3c6cfaf41e0514b875ba7a85f0413c8e288a","response-headers":{"Accept-Ranges":"bytes","Age":"0","Connection":"keep-alive","Content-Length":"52547","Content-Type":"text/csv","Date":"Thu, 26 Oct 2023 00:22:50 GMT","Etag":"\"626ad58a-cd43\"","Last-Modified":"Thu, 28 Apr 2022 17:57:30 GMT","Server":"nginx","Strict-Transport-Security":"max-age=300","Via":"1.1 varnish, 1.1 varnish","X-Cache":"MISS, MISS","X-Cache-Hits":"0, 0","X-Pantheon-Styx-Hostname":"styx-fe3fe4-c-78677fb8cb-29sfg","X-Served-By":"cache-ams21023-AMS, cache-iad-kcgs7200107-IAD","X-Styx-Req-Id":"cc09d7f3-7395-11ee-901a-1a7b0fe01fc4","X-Timer":"S1698279770.331345,VS0,VE335"},"ssl-verify":true,"status":"200"}