{"elapsed":"0.516","endpoint-url":"https://cbccrmdata.blob.core.windows.net/noteattachment/CBC-Fees-and-charges-Developer-agreement-contributions-Developer%20Agreement%20Contributions_20201202.csv","entry-date":"2023-04-16T00:20:47.124032","request-headers":{"Accept":"*/*","Accept-Encoding":"gzip, deflate","Connection":"keep-alive","User-Agent":"DLUHC Digital Land"},"response-headers":{"Content-Length":"215","Content-Type":"application/xml","Date":"Sun, 16 Apr 2023 00:21:40 GMT","Server":"Windows-Azure-Blob/1.0 Microsoft-HTTPAPI/2.0","x-ms-request-id":"b2bb87ab-f01e-004a-40f9-6f0b60000000","x-ms-version":"2009-09-19"},"ssl-verify":true,"status":"404"}