{"elapsed":"0.134","endpoint-url":"https://eryc.link/developertransactions  ","entry-date":"2022-04-12T00:19:51.598175","request-headers":{"Accept":"*/*","Accept-Encoding":"gzip, deflate","Connection":"keep-alive","User-Agent":"DLUHC Digital Land"},"response-headers":{"Accept-Ranges":"bytes","Age":"10854","Connection":"keep-alive","Content-Length":"3633","Content-Type":"text/html","Date":"Mon, 11 Apr 2022 21:19:58 GMT","ETag":"\"5afd315a4cc6039b4dfd18cfa046304c\"","Last-Modified":"Fri, 02 Apr 2021 09:36:32 GMT","Server":"AmazonS3","Via":"1.1 3ce1b04fdf4b78c695ea1764363d1f38.cloudfront.net (CloudFront)","X-Amz-Cf-Id":"TB8yRfqfhbsv3Mf2B_T8OyUWxBnx5xPnw8iSKXdIw3gEJmfXojQyBA==","X-Amz-Cf-Pop":"IAD79-C3","X-Cache":"Hit from cloudfront","x-amz-version-id":"null"},"ssl-verify":true,"status":"200"}