{"bytes":24011,"elapsed":"0.703","endpoint-url":"https://cdn-eastherts.onwebcurl.com/s3fs-public/2021-11/East%20Herts%20Council%20-%20CVS%20File%203%20-%20developer-agreement-transaction_2020-21.xlsx","entry-date":"2022-02-18T01:15:10.239050","request-headers":{"Accept":"*/*","Accept-Encoding":"gzip, deflate","Connection":"keep-alive","User-Agent":"DLUHC Digital Land"},"resource":"c52a6d054088bb8b98d9522a6948fdf3ed02579101047c173b27635421b2c0d3","response-headers":{"Accept-Ranges":"bytes","Cache-Control":"max-age=3600","Connection":"Keep-Alive","Content-Length":"24011","Content-Type":"application/vnd.openxmlformats-officedocument.spreadsheetml.sheet","Date":"Fri, 18 Feb 2022 01:18:24 GMT","Last-Modified":"Wed, 24 Nov 2021 21:31:45 GMT","X-HW":"1645147103.dop178.dc2.t,1645147103.cds060.dc2.shn,1645147103.dop178.dc2.t,1645147104.cds192.dc2.p","etag":"\"1fb3674a69c7846bc97d0c9fb9e0a54f\"","strict-transport-security":"max-age=15552000; includeSubDomains; preload","x-amz-request-id":"tx000000000000112d29d48-00620ef3e0-1a043886-fra1a","x-rgw-object-type":"Normal"},"ssl-verify":true,"status":"200"}