{"elapsed":"0.541","endpoint-url":"https://tunbridgewells.gov.uk/__data/assets/file/0008/377153/developer-agreement-transaction_20211203.csv","entry-date":"2022-01-03T01:06:11.265623","request-headers":{"Accept":"*/*","Accept-Encoding":"gzip, deflate","Connection":"keep-alive","User-Agent":"DLUHC Digital Land"},"resource":"325dc8a93de480d6be69e46a30b6bd365c9d4eec665a3f25e35b2f971cde64d1","response-headers":{"Accept-Ranges":"bytes","Cache-Control":"max-age=21600","Connection":"keep-alive","Content-Length":"2281","Content-Type":"application/octet-stream","Date":"Mon, 03 Jan 2022 01:08:49 GMT","ETag":"\"61c2e82e-8e9\"","Expires":"Mon, 03 Jan 2022 07:08:49 GMT","Last-Modified":"Wed, 22 Dec 2021 08:56:14 GMT","Server":"openresty","Via":"1.1 mkip5 (squid/3.5.20)","X-Cache":"MISS from mkip5","X-Cache-Lookup":"HIT from mkip5:3128"},"ssl-verify":true,"status":"200"}