{"elapsed":"0.405","endpoint-url":"https://cbccrmdata.blob.core.windows.net/noteattachment/CBC-Fees-and-charges-Developer-agreement-Developer%20Agreements_20201202.csv","entry-date":"2022-03-03T00:26:38.511806","request-headers":{"Accept":"*/*","Accept-Encoding":"gzip, deflate","Connection":"keep-alive","User-Agent":"DLUHC Digital Land"},"response-headers":{"Content-Length":"215","Content-Type":"application/xml","Date":"Thu, 03 Mar 2022 00:26:44 GMT","Server":"Windows-Azure-Blob/1.0 Microsoft-HTTPAPI/2.0","x-ms-request-id":"ed8a15dd-a01e-001a-2495-2ec930000000","x-ms-version":"2009-09-19"},"ssl-verify":true,"status":"404"}