{"elapsed":"1.024","endpoint-url":"https://www.southhams.gov.uk/developer-agreement-contribution","entry-date":"2023-11-22T00:21:25.464702","request-headers":{"Accept":"*/*","Accept-Encoding":"gzip, deflate","Connection":"keep-alive","User-Agent":"DLUHC Digital Land"},"resource":"dc54c8a3e945e684ff63739f222441de6e5a0069a3f24eb9632ebacb67b53ef1","response-headers":{"Accept-Ranges":"bytes","Connection":"keep-alive","Content-Length":"16584","Content-Type":"application/vnd.openxmlformats-officedocument.spreadsheetml.sheet","Date":"Wed, 22 Nov 2023 00:25:29 GMT","ETag":"\"6479ddae-40c8\"","Last-Modified":"Fri, 02 Jun 2023 12:16:46 GMT","Server":"nginx","Via":"1.1 a205375e18fe141924bfb6a4f09d1f88.cloudfront.net (CloudFront)","X-Amz-Cf-Id":"1ZdViLoY1uOR-bBK_4Ua1mrEPWdZz8SJ8cCNzhT4HpUOVuh61YahBw==","X-Amz-Cf-Pop":"DFW56-P1","X-Cache":"Miss from cloudfront","X-Content-Type-Options":"nosniff"},"ssl-verify":true,"status":"200"}