{"elapsed":"0.339","endpoint-url":"https://www.copeland.gov.uk/attachments/developer-agreement-contribution","entry-date":"2022-08-14T00:23:48.908646","request-headers":{"Accept":"*/*","Accept-Encoding":"gzip, deflate","Connection":"keep-alive","User-Agent":"DLUHC Digital Land"},"response-headers":{"Accept-Ranges":"bytes","Age":"0","Cache-Control":"public, max-age=10800","Connection":"keep-alive","Content-Encoding":"gzip","Content-Language":"en","Content-Type":"text/html; charset=utf-8","Date":"Sun, 14 Aug 2022 00:24:30 GMT","Etag":"\"1660350217-1\"","Expires":"Sun, 19 Nov 1978 05:00:00 GMT","Last-Modified":"Sat, 13 Aug 2022 00:23:37 GMT","Link":"<https://www.copeland.gov.uk/attachments/developer-agreement-contribution>; rel=\"canonical\",<https://www.copeland.gov.uk/node/45661>; rel=\"shortlink\"","Permissions-Policy":"interest-cohort=()","Server":"nginx","Transfer-Encoding":"chunked","Vary":"Cookie,Accept-Encoding","X-Cache-Backend":"c185_web_2","X-Cache-Cacheable":"YES","X-Cache-Host":"c185-varnish-1","X-Cache-Result":"MISS","X-Content-Type-Options":"nosniff","X-Drupal-Cache":"HIT","X-Frame-Options":"SAMEORIGIN","X-Varnish":"9420204","grace":"none"},"ssl-verify":true,"status":"200"}