{"elapsed":"1.138","endpoint-url":"https://www.arun.gov.uk/developer-agreement-transaction-latest","entry-date":"2023-08-20T00:20:35.478002","request-headers":{"Accept":"*/*","Accept-Encoding":"gzip, deflate","Connection":"keep-alive","Cookie":"JSESSIONID=0B1FF92E497FC65EA8ADB610417AB51D; TS01f9252f=010a4d52f3e4272fa4b6512225ea7ec9b49c69f7f52019280fa5030132637a4dcd837cf930bcef258191107b58d41b9b8396529e38","User-Agent":"DLUHC Digital Land"},"resource":"40cd6213f513169e46c618d7a3462a1daea3e208d2f0eae0a25addeb27140ecb","response-headers":{"Connection":"keep-alive","Content-Disposition":"inline; filename=developer-agreement-transaction_2021-22.csv","Content-Length":"16063","Content-Type":"text/csv","Date":"Sun, 20 Aug 2023 00:23:22 GMT","Strict-Transport-Security":"max-age=31536000; includeSubDomains","X-Content-Type-Options":"nosniff","X-Frame-Options":"SAMEORIGIN","X-Responder":"RD2","X-XSS-Protection":"1; mode=block"},"ssl-verify":true,"status":"200"}