{"elapsed":"1.492","endpoint-url":"https://www.hertfordshire.gov.uk/developer-agreement","entry-date":"2024-01-13T00:22:12.639142","request-headers":{"Accept":"*/*","Accept-Encoding":"gzip, deflate","Connection":"keep-alive","User-Agent":"DLUHC Digital Land"},"resource":"fbd716804eda0c8d0474ba966e38a32359dc716f2cbc6d828775c6054a69c980","response-headers":{"accept-ranges":"bytes","access-control-allow-headers":"*","access-control-allow-methods":"GET, OPTIONS","cache-control":"public,no-transform","connection":"close","content-length":"3080","content-security-policy":"frame-ancestors 'self';","content-type":"application/octet-stream","date":"Sat, 13 Jan 2024 00:22:37 GMT","last-modified":"Tue, 29 Dec 2020 11:13:21 GMT","x-age":"0","x-cacheable":"NO:Not Cacheable, ttl <0s","x-contensis-viewer-groups":"0","x-grace":"72h","x-host":"live-hcc.cloud.contensis.com","x-origin-server":"z-hcc-WEB2","x-server-name":"z-hcc-CACHE1","x-ua-compatible":"IE=edge,chrome=1","x-varnish":"357690499","x-varnish-authentication":"skip"},"ssl-verify":true,"status":"200"}