{"elapsed":"2.277","endpoint-url":"https://southhams.gov.uk/developer-agreement-contribution","entry-date":"2023-11-15T00:19:35.566814","request-headers":{"Accept":"*/*","Accept-Encoding":"gzip, deflate","Connection":"keep-alive","User-Agent":"DLUHC Digital Land"},"resource":"dc54c8a3e945e684ff63739f222441de6e5a0069a3f24eb9632ebacb67b53ef1","response-headers":{"Accept-Ranges":"bytes","Connection":"keep-alive","Content-Length":"16584","Content-Type":"application/vnd.openxmlformats-officedocument.spreadsheetml.sheet","Date":"Wed, 15 Nov 2023 00:21:02 GMT","ETag":"\"6479ddae-40c8\"","Last-Modified":"Fri, 02 Jun 2023 12:16:46 GMT","Server":"nginx","Via":"1.1 9df316641adfdaf044ba4a0279382a60.cloudfront.net (CloudFront)","X-Amz-Cf-Id":"MiUxmDCt3K-rTa48N8BLZ_sxU2iJQmFPj7VsTH-LXJEYvMICNA2LAw==","X-Amz-Cf-Pop":"SFO53-P1","X-Cache":"Miss from cloudfront","X-Content-Type-Options":"nosniff"},"ssl-verify":true,"status":"200"}