{"elapsed":"0.19","endpoint-url":"https://www.broxbourne.gov.uk/developer-agreement-contributions-19/20","entry-date":"2023-01-08T00:23:20.413330","request-headers":{"Accept":"*/*","Accept-Encoding":"gzip, deflate","Connection":"keep-alive","Cookie":"PHPSESSID=OMoe5E5cJygdcwoLT5QEJ6ZVPqWtbAADuSFs2QMwXyVH962VIRumxt0b8qDAZ2Ci","User-Agent":"DLUHC Digital Land"},"resource":"8f9747e53a2edbc5da5ecd95b90dca06a644a72ea346d12cc690057e79e1caac","response-headers":{"Accept-Ranges":"bytes","Cache-Control":"max-age=0, must-revalidate, post-check=0, pre-check=0, private","Connection":"keep-alive","Content-Disposition":"inline; filename=\"developer_agreement_contribution_20201123.csv\"","Content-Length":"4158","Content-Type":"application/vnd.ms-excel","Date":"Sun, 08 Jan 2023 00:27:12 GMT","Expires":"Sun, 08 Jan 2023 00:27:12 GMT","Last-Modified":"Wed, 29 Dec 2021 16:21:57 GMT","Pragma":"public","Server":"Web Server","X-Content-Type-Options":"nosniff","X-Frame-Options":"SAMEORIGIN","X-XSS-Protection":"1; mode=block"},"ssl-verify":true,"status":"200"}