{"elapsed":"0.148","endpoint-url":"https://www.newark-sherwooddc.gov.uk/media/newark-and-sherwood/images-and-files/business/pdf/S106-developer-agreement_2020331.csv","entry-date":"2024-01-07T00:23:47.345279","request-headers":{"Accept":"*/*","Accept-Encoding":"gzip, deflate","Connection":"keep-alive","User-Agent":"DLUHC Digital Land"},"resource":"0e4e4920dae85cfbc313362b9e39b11572f165d113d949ec87d7024a5d60e881","response-headers":{"Accept-Ranges":"bytes","Cache-Control":"max-age=172800","Connection":"keep-alive","Content-Length":"385","Content-Type":"text/csv","Date":"Sun, 07 Jan 2024 00:26:56 GMT","ETag":"\"181-5cb649f0909a0\"","Expires":"Tue, 09 Jan 2024 00:26:56 GMT","Last-Modified":"Tue, 07 Sep 2021 09:45:08 GMT","Server":"Apache","Strict-Transport-Security":"max-age=31536000; includeSubDomains","Vary":"User-Agent","X-Frame-Options":"SAMEORIGIN"},"ssl-verify":true,"status":"200"}