{"elapsed":"0.448","endpoint-url":"https://cdn-eastherts.onwebcurl.com/s3fs-public/2021-11/East%20Herts%20Council%20-%20CVS%20File%201%20-%20developer-agreement.xlsx","entry-date":"2022-07-20T00:20:26.439593","request-headers":{"Accept":"*/*","Accept-Encoding":"gzip, deflate","Connection":"keep-alive","User-Agent":"DLUHC Digital Land"},"resource":"42017351dca2220a2a7e2d74bebbfd44a162a168ecccc10bc66f5d5721313b76","response-headers":{"Accept-Ranges":"bytes","Cache-Control":"max-age=3600","Connection":"Keep-Alive","Content-Length":"16454","Content-Type":"application/vnd.openxmlformats-officedocument.spreadsheetml.sheet","Date":"Wed, 20 Jul 2022 00:22:52 GMT","Last-Modified":"Fri, 26 Nov 2021 16:17:26 GMT","Vary":"Access-Control-Request-Headers,Access-Control-Request-Method,Origin","X-HW":"1658276571.dop165.dc2.t,1658276571.cds203.dc2.shn,1658276571.dop165.dc2.t,1658276572.cds093.dc2.pr","etag":"\"3b54d3eef667bf8bce333a8b0d12fe3d\"","strict-transport-security":"max-age=15552000; includeSubDomains; preload","x-amz-request-id":"tx00000000000003e0d034d-0062d74adb-280ab81f-fra1a","x-rgw-object-type":"Normal"},"ssl-verify":true,"status":"200"}