{"elapsed":"0.183","endpoint-url":"https://eryc.link/developertransactions  ","entry-date":"2021-08-04T00:57:40.361872","request-headers":{"Accept":"*/*","Accept-Encoding":"gzip, deflate","Connection":"keep-alive","User-Agent":"Digital Land"},"response-headers":{"Accept-Ranges":"bytes","Age":"65645","Connection":"keep-alive","Content-Length":"3633","Content-Type":"text/html","Date":"Tue, 03 Aug 2021 06:44:44 GMT","ETag":"\"5afd315a4cc6039b4dfd18cfa046304c\"","Last-Modified":"Fri, 02 Apr 2021 09:36:32 GMT","Server":"AmazonS3","Via":"1.1 9317f1a4c7320bdeb8f38066b985748b.cloudfront.net (CloudFront)","X-Amz-Cf-Id":"iB80YgvUfRWhXnsNBRZtWTJx3VrK9KKcH8x4mTPk7SBz2ZX5FAX4bw==","X-Amz-Cf-Pop":"IAD66-C2","X-Cache":"Hit from cloudfront"},"ssl-verify":true,"status":"200"}