{"elapsed":"2.479","endpoint-url":"https://www.iow.gov.uk/PlanningObligations/Download.ashx?type=Extract&extract=Agreements","entry-date":"2023-05-17T00:22:59.137559","request-headers":{"Accept":"*/*","Accept-Encoding":"gzip, deflate","Connection":"keep-alive","User-Agent":"DLUHC Digital Land"},"response-headers":{"Date":"Wed, 17 May 2023 00:22:31 GMT","Server":"Microsoft-IIS/10.0","Strict-Transport-Security":"max-age=2592000","Transfer-Encoding":"chunked","X-Powered-By":"ASP.NET"},"ssl-verify":true,"status":"404"}