{"elapsed":"0.754","endpoint-url":"https://www.copeland.gov.uk/attachments/developer-agreement-contribution","entry-date":"2023-05-17T00:22:59.137559","request-headers":{"Accept":"*/*","Accept-Encoding":"gzip, deflate","Connection":"keep-alive","User-Agent":"DLUHC Digital Land"},"response-headers":{"Accept-Ranges":"bytes","Age":"0","Cache-Control":"public, max-age=10800","Connection":"keep-alive","Content-Encoding":"gzip","Content-Language":"en","Content-Length":"7567","Content-Type":"text/html; charset=utf-8","Date":"Wed, 17 May 2023 00:23:58 GMT","Etag":"\"1684269183-1\"","Expires":"Sun, 19 Nov 1978 05:00:00 GMT","Last-Modified":"Tue, 16 May 2023 20:33:03 GMT","Link":"<https://www.copeland.gov.uk/attachments/developer-agreement-contribution>; rel=\"canonical\",<https://www.copeland.gov.uk/node/45661>; rel=\"shortlink\"","Server":"nginx","Vary":"Cookie,Accept-Encoding","X-Cache-Backend":"c185_web_1","X-Cache-Cacheable":"YES","X-Cache-Host":"c185-varnish-1","X-Cache-Result":"MISS","X-Content-Type-Options":"nosniff","X-Drupal-Cache":"HIT","X-Frame-Options":"SAMEORIGIN","X-Varnish":"10017619","grace":"none"},"ssl-verify":true,"status":"200"}