{"elapsed":"0.704","endpoint-url":"https://www.broxbourne.gov.uk/downloads/file/1303/developer-agreements","entry-date":"2022-12-14T00:21:04.478861","request-headers":{"Accept":"*/*","Accept-Encoding":"gzip, deflate","Connection":"keep-alive","User-Agent":"DLUHC Digital Land"},"response-headers":{"Cache-Control":"max-age=0, must-revalidate, private","Connection":"keep-alive","Content-Type":"text/html; charset=UTF-8","Date":"Wed, 14 Dec 2022 00:21:09 GMT","Expires":"Wed, 14 Dec 2022 00:21:09 GMT","Server":"Web Server","Set-Cookie":"PHPSESSID=dzsrhUvSq4yPoJhh-a%2Cs0p8oKmiqctfJK5PWAAOyMcUULB65ps7TofgmjtiyupZ7; path=/; secure; HttpOnly; HttpOnly;SameSite=None; Secure","Transfer-Encoding":"chunked","X-Content-Type-Options":"nosniff","X-Frame-Options":"SAMEORIGIN","X-XSS-Protection":"1; mode=block"},"ssl-verify":true,"status":"404"}