{"elapsed":"0.779","endpoint-url":"https://www.westdevon.gov.uk/developer-agreement-transaction","entry-date":"2023-12-06T00:20:26.440500","request-headers":{"Accept":"*/*","Accept-Encoding":"gzip, deflate","Connection":"keep-alive","User-Agent":"DLUHC Digital Land"},"resource":"2c86a4234364632ee79a2af6a72c5657be34bc0859c8102621b19961dfa1983f","response-headers":{"Accept-Ranges":"bytes","Age":"130","Connection":"keep-alive","Content-Length":"13040","Content-Type":"application/vnd.openxmlformats-officedocument.spreadsheetml.sheet","Date":"Wed, 06 Dec 2023 00:22:45 GMT","ETag":"\"647f3ebf-32f0\"","Last-Modified":"Tue, 06 Jun 2023 14:12:15 GMT","Server":"nginx","Via":"1.1 75109f22d44404e68915a641fc09f102.cloudfront.net (CloudFront)","X-Amz-Cf-Id":"lxYuNsvSQtwZvum7taIPn324kSVCt2VwSAmfua9OpBccAwRpNy-2PA==","X-Amz-Cf-Pop":"SFO53-P1","X-Cache":"Hit from cloudfront","X-Content-Type-Options":"nosniff"},"ssl-verify":true,"status":"200"}