{"elapsed":"1.016","endpoint-url":"https://www.carlisle.gov.uk/Portals/24/Documents/Evidence_Base/IFS/developer-agreement-contribution20201230.csv","entry-date":"2022-10-30T00:28:19.500485","request-headers":{"Accept":"*/*","Accept-Encoding":"gzip, deflate","Connection":"keep-alive","User-Agent":"DLUHC Digital Land"},"resource":"c268154f7c5fd0d4158bfd35de69711d257e348414cbf2c0ef88102596ec38ec","response-headers":{"Accept-Ranges":"bytes","CF-Cache-Status":"MISS","CF-RAY":"76200c7c1ec1cee1-SJC","Cache-Control":"max-age=691200","Connection":"keep-alive","Content-Length":"4867","Content-Type":"application/octet-stream","Date":"Sun, 30 Oct 2022 00:31:34 GMT","NEL":"{\"success_fraction\":0,\"report_to\":\"cf-nel\",\"max_age\":604800}","Report-To":"{\"endpoints\":[{\"url\":\"https:\\/\\/a.nel.cloudflare.com\\/report\\/v3?s=oHHRiAMZOW3U0a%2BrYnBz9X5kLVGIol2nVWFaO%2B%2BcaS7KG4MIckWXlSwuipiredhE7Gc4Qefdc4xkGF%2B8%2F0QcQm2fX2gjg2EQSUaWWbfQjArA0MKbE80aGWPc3eKgZb8ti7XQqfw%3D\"}],\"group\":\"cf-nel\",\"max_age\":604800}","Server":"cloudflare","Vary":"Accept-Encoding","etag":"\"4ade1e8830e8d61:0\"","last-modified":"Mon, 11 Jan 2021 15:43:39 GMT","strict-transport-security":"max-age=63072000","x-content-type-options":"nosniff","x-frame-options":"SAMEORIGIN","x-ua-compatible":"IE=edge","x-xss-protection":"1; mode=block"},"ssl-verify":true,"status":"200"}