{"elapsed":"0.745","endpoint-url":"https://www3.halton.gov.uk/Pages/planning/pdf/registers/developeragreement.csv","entry-date":"2022-07-01T00:25:48.733293","request-headers":{"Accept":"*/*","Accept-Encoding":"gzip, deflate","Connection":"keep-alive","User-Agent":"DLUHC Digital Land"},"response-headers":{"Accept-Ranges":"bytes","Cache-Control":"private,max-age=0","Content-Length":"715","Content-Type":"text/html","Date":"Fri, 01 Jul 2022 00:26:00 GMT","Expires":"Thu, 16 Jun 2022 00:26:05 GMT","MicrosoftSharePointTeamServices":"16.0.0.10349: 1; RequireReadOnly","Public-Extension":"http://schemas.microsoft.com/repl-2","SPIisLatency":"1","SPRequestDuration":"12","SPRequestGuid":"36954ca0-354a-00bb-7df2-70796dd43e58","Server":"Microsoft-IIS/8.5","Strict-Transport-Security":"max-age=31536000","X-FRAME-OPTIONS":"SAMEORIGIN","X-Powered-By":"nosniff, ARR/3.0","X-SharePointHealthScore":"0","request-id":"36954ca0-354a-00bb-7df2-70796dd43e58"},"ssl-verify":true,"status":"404"}