{"elapsed":"0.137","endpoint-url":"https://www.carlisle.gov.uk/Portals/24/Documents/Evidence_Base/IFS/developer-agreement-transactions20201230.csv","entry-date":"2023-05-05T00:23:45.232529","request-headers":{"Accept":"*/*","Accept-Encoding":"gzip, deflate","Connection":"keep-alive","User-Agent":"DLUHC Digital Land"},"resource":"1ac5852856bd9ed721caba9ed88a27ca6e65776f2ee82b7e717e6d348ad3f9a8","response-headers":{"Accept-Ranges":"bytes","Age":"173024","CF-Cache-Status":"HIT","CF-RAY":"7c24da312e244683-DFW","Cache-Control":"max-age=691200","Connection":"keep-alive","Content-Length":"2151","Content-Type":"application/octet-stream","Date":"Fri, 05 May 2023 00:26:29 GMT","NEL":"{\"success_fraction\":0,\"report_to\":\"cf-nel\",\"max_age\":604800}","Report-To":"{\"endpoints\":[{\"url\":\"https:\\/\\/a.nel.cloudflare.com\\/report\\/v3?s=IXNrUwHmZHuIkkXYK%2FfQPZsYun86%2FktyNvqafHMRX7scLX%2FEdmL4jhb76oRvS6qvJjrffc59UCC8lmC4ToXe76iBsYR6L5z28ENLqhir3l2KVT4n1YaMcl%2BOIoc9mG9EVe7R7hE%3D\"}],\"group\":\"cf-nel\",\"max_age\":604800}","Server":"cloudflare","Vary":"Accept-Encoding","etag":"\"df75269030e8d61:0\"","last-modified":"Mon, 11 Jan 2021 15:43:52 GMT","strict-transport-security":"max-age=63072000","x-content-type-options":"nosniff","x-frame-options":"SAMEORIGIN","x-ua-compatible":"IE=edge","x-xss-protection":"1; mode=block"},"ssl-verify":true,"status":"200"}