{"elapsed":"0.569","endpoint-url":"https://cbccrmdata.blob.core.windows.net/noteattachment/CBC-Fees-and-charges-Developer-agreement-Developer%20Agreements_20201202.csv","entry-date":"2023-11-10T00:20:18.383458","request-headers":{"Accept":"*/*","Accept-Encoding":"gzip, deflate","Connection":"keep-alive","User-Agent":"DLUHC Digital Land"},"response-headers":{"Content-Length":"215","Content-Type":"application/xml","Date":"Fri, 10 Nov 2023 00:20:29 GMT","Server":"Windows-Azure-Blob/1.0 Microsoft-HTTPAPI/2.0","x-ms-request-id":"2301569b-601e-0005-2f6b-137a34000000","x-ms-version":"2009-09-19"},"ssl-verify":true,"status":"404"}