{"elapsed":"0.22","endpoint-url":"https://cdn-eastherts.onwebcurl.com/s3fs-public/2021-11/East%20Herts%20Council%20-%20CVS%20File%203%20-%20developer-agreement-transaction_2020-21.xlsx","entry-date":"2024-01-24T00:24:27.862730","request-headers":{"Accept":"*/*","Accept-Encoding":"gzip, deflate","Connection":"keep-alive","Cookie":"__cf_bm=J2mOEJyMW876PVkRGbCasOb65KJ4Z1g9T9guPdGjw9I-1706055877-1-AfRx3dttec+piniDm0se2s1gVWIDcqbCxBSB60T5dwpNMs7kreMb/8WWBaqM4buNlB9G3R1Yt5P6Atz8rhPlLFI=","User-Agent":"DLUHC Digital Land"},"resource":"c52a6d054088bb8b98d9522a6948fdf3ed02579101047c173b27635421b2c0d3","response-headers":{"Accept-Ranges":"bytes","CF-Cache-Status":"MISS","CF-RAY":"84a427076f059c5e-IAD","Cache-Control":"max-age=3600","Connection":"keep-alive","Content-Length":"24011","Content-Type":"application/vnd.openxmlformats-officedocument.spreadsheetml.sheet","Date":"Wed, 24 Jan 2024 00:27:45 GMT","Server":"cloudflare","etag":"\"1fb3674a69c7846bc97d0c9fb9e0a54f\"","last-modified":"Wed, 24 Nov 2021 21:31:45 GMT","strict-transport-security":"max-age=15552000; includeSubDomains; preload","vary":"Origin, Access-Control-Request-Headers, Access-Control-Request-Method, Accept-Encoding","x-amz-request-id":"tx00000b531c1d4d694cd9e-0065b05981-cc24f42f-fra1b","x-do-cdn-uuid":"f33171ba-723d-43ea-8ed0-cfba548481a9","x-envoy-upstream-healthchecked-cluster":"","x-rgw-object-type":"Normal"},"ssl-verify":true,"status":"200"}