{"elapsed":"0.683","endpoint-url":"https://cdn-eastherts.onwebcurl.com/s3fs-public/2021-11/East%20Herts%20Council%20-%20CVS%20File%203%20-%20developer-agreement-transaction_2020-21.xlsx","entry-date":"2023-03-10T00:22:51.369765","request-headers":{"Accept":"*/*","Accept-Encoding":"gzip, deflate","Connection":"keep-alive","User-Agent":"DLUHC Digital Land"},"resource":"c52a6d054088bb8b98d9522a6948fdf3ed02579101047c173b27635421b2c0d3","response-headers":{"Accept-Ranges":"bytes","Cache-Control":"max-age=3600","Connection":"Keep-Alive","Content-Length":"24011","Content-Type":"application/vnd.openxmlformats-officedocument.spreadsheetml.sheet","Date":"Fri, 10 Mar 2023 00:36:01 GMT","Last-Modified":"Wed, 24 Nov 2021 21:31:45 GMT","Vary":"Access-Control-Request-Headers,Access-Control-Request-Method,Origin","X-HW":"1678408560.dop102.dc2.t,1678408560.cds058.dc2.shn,1678408560.dop102.dc2.t,1678408561.cds171.dc2.pr","etag":"\"1fb3674a69c7846bc97d0c9fb9e0a54f\"","strict-transport-security":"max-age=15552000; includeSubDomains; preload","x-amz-request-id":"tx000000000000081a9af55-00640a7b71-852b6119-fra1b","x-rgw-object-type":"Normal"},"ssl-verify":true,"status":"200"}