{"elapsed":"0.282","endpoint-url":"https://eryc.link/developertransactions  ","entry-date":"2021-12-10T01:03:54.912622","request-headers":{"Accept":"*/*","Accept-Encoding":"gzip, deflate","Connection":"keep-alive","User-Agent":"Digital Land"},"response-headers":{"Accept-Ranges":"bytes","Age":"85832","Connection":"keep-alive","Content-Length":"3633","Content-Type":"text/html","Date":"Thu, 09 Dec 2021 01:14:35 GMT","ETag":"\"5afd315a4cc6039b4dfd18cfa046304c\"","Last-Modified":"Fri, 02 Apr 2021 09:36:32 GMT","Server":"AmazonS3","Via":"1.1 b5a3a07d269412210ea111017ec1157f.cloudfront.net (CloudFront)","X-Amz-Cf-Id":"7I6avSmPZCd2HkxzzsXWAV1PfBvYp4ZIuuEycQSczXBQd4S5EQg59g==","X-Amz-Cf-Pop":"IAD79-C3","X-Cache":"Hit from cloudfront","x-amz-version-id":"null"},"ssl-verify":true,"status":"200"}