{"elapsed":"1.081","endpoint-url":"https://www.arun.gov.uk/developer-agreement-latest","entry-date":"2022-11-20T00:24:54.083003","request-headers":{"Accept":"*/*","Accept-Encoding":"gzip, deflate","Connection":"keep-alive","Cookie":"JSESSIONID=9A52EFE3E3F9C51F260F7636A49399E4; TS0159864e=015de49753505802b335d50fd2ab041133f1e9b14f764ebbacca7fda82db69de3c6ba771b5a2be087d43ef3c281099c0378ab93ea2","User-Agent":"DLUHC Digital Land"},"resource":"3d9ad9150854d2a1faeece2cf4dea3f2bccc40e25a88aff7f388e0212f22cbc4","response-headers":{"Connection":"keep-alive","Content-Disposition":"inline; filename=developer-agreement_2021-22.csv","Content-Length":"26907","Content-Type":"text/csv","Strict-Transport-Security":"max-age=15768000","X-Responder":"RD1"},"ssl-verify":true,"status":"200"}