{"elapsed":"0.21","endpoint-url":"https://eryc.link/developertransactions  ","entry-date":"2022-07-16T00:24:20.400617","request-headers":{"Accept":"*/*","Accept-Encoding":"gzip, deflate","Connection":"keep-alive","User-Agent":"DLUHC Digital Land"},"response-headers":{"Accept-Ranges":"bytes","Age":"50188","Connection":"keep-alive","Content-Length":"3633","Content-Type":"text/html","Date":"Fri, 15 Jul 2022 10:28:57 GMT","ETag":"\"5afd315a4cc6039b4dfd18cfa046304c\"","Last-Modified":"Fri, 02 Apr 2021 09:36:32 GMT","Server":"AmazonS3","Vary":"Accept-Encoding","Via":"1.1 5840e9664aef77d9be1f708259e60d56.cloudfront.net (CloudFront)","X-Amz-Cf-Id":"yKiysuvxuL7cVI-qDvJPPNZHbPeMX7kOaOZTlFMPRclK5k4TDSy-GA==","X-Amz-Cf-Pop":"IAD89-P2","X-Cache":"Hit from cloudfront","x-amz-version-id":"null"},"ssl-verify":true,"status":"200"}