{"elapsed":"0.228","endpoint-url":"https://www.eastcambs.gov.uk/sites/default/files/developer-agreement-transaction_2020-10-12.csv","entry-date":"2023-09-02T00:19:28.177945","request-headers":{"Accept":"*/*","Accept-Encoding":"gzip, deflate","Connection":"keep-alive","User-Agent":"DLUHC Digital Land"},"resource":"352716a0b6c58e5ed33dd41dd1b452aaa150bcc97f37ccd820b023c84086642f","response-headers":{"Accept-Ranges":"bytes","Age":"0","Connection":"keep-alive","Content-Length":"25144","Content-Type":"text/csv","Date":"Sat, 02 Sep 2023 00:21:42 GMT","Etag":"\"626ad58a-6238\"","Last-Modified":"Thu, 28 Apr 2022 17:57:30 GMT","Server":"nginx","Strict-Transport-Security":"max-age=300","Via":"1.1 varnish, 1.1 varnish","X-Cache":"MISS, MISS","X-Cache-Hits":"0, 0","X-Pantheon-Styx-Hostname":"styx-fe3fe4-c-7b66765c8f-5pmcl","X-Served-By":"cache-ams12731-AMS, cache-iad-kiad7000122-IAD","X-Styx-Req-Id":"b0e660df-4926-11ee-839f-ba52a8c2180a","X-Timer":"S1693614102.999393,VS0,VE142"},"ssl-verify":true,"status":"200"}