{"elapsed":"0.748","endpoint-url":"https://www.broxbourne.gov.uk/downloads/file/1303/developer-agreements","entry-date":"2022-01-27T01:04:04.559559","request-headers":{"Accept":"*/*","Accept-Encoding":"gzip, deflate","Connection":"keep-alive","User-Agent":"DLUHC Digital Land"},"response-headers":{"Cache-Control":"max-age=0, must-revalidate, private","Connection":"keep-alive","Content-Type":"text/html; charset=UTF-8","Date":"Thu, 27 Jan 2022 01:04:08 GMT","Expires":"Thu, 27 Jan 2022 01:04:08 GMT","Server":"Apache","Set-Cookie":"PHPSESSID=tJr54EBC-naOCVFI8GDoH9fY%2CrRKhfW2S9heHoaE3eIHOVgHy2Li05St6fHqf42L; path=/; secure; HttpOnly; HttpOnly;SameSite=None; Secure","Transfer-Encoding":"chunked","X-Content-Type-Options":"nosniff","X-Frame-Options":"SAMEORIGIN","X-XSS-Protection":"1; mode=block"},"ssl-verify":true,"status":"404"}