{"elapsed":"1.022","endpoint-url":"https://epsom-ewell.gov.uk/sites/default/files/documents/residents/planning/planning-policy/community-infrastructure-levy-cil/developer-agreement.csv","entry-date":"2022-08-02T00:23:48.477175","request-headers":{"Accept":"*/*","Accept-Encoding":"gzip, deflate","Connection":"keep-alive","User-Agent":"DLUHC Digital Land"},"resource":"3b2b2840f5d22b045794f23e9b9c4bda1571217fb5aad71e22a4f44a0ff2d20b","response-headers":{"Accept-Ranges":"bytes","Age":"0","Connection":"keep-alive","Content-Length":"2684","Content-Type":"text/csv","Date":"Tue, 02 Aug 2022 00:24:02 GMT","Etag":"\"62b99a1b-a7c\"","Last-Modified":"Mon, 27 Jun 2022 11:52:59 GMT","Server":"nginx","Strict-Transport-Security":"max-age=300","Traceparent":"00-d583d92c65b549918452d36501c024e2-3d67defbc87e5d30-00","Via":"1.1 varnish, 1.1 varnish","X-Cache":"MISS, MISS","X-Cache-Hits":"0, 0","X-Cloud-Trace-Context":"d583d92c65b549918452d36501c024e2/4424750331896683824;o=0","X-Pantheon-Styx-Hostname":"styx-fe1fe2-c-6c94847858-cc9tj","X-Served-By":"cache-ams21054-AMS, cache-bur-kbur8200175-BUR","X-Styx-Req-Id":"68b0ca3d-11f9-11ed-b3bf-4e71440f5486","X-Timer":"S1659399841.430900,VS0,VE704"},"ssl-verify":true,"status":"200"}