{"elapsed":"0.907","endpoint-url":"https://www3.halton.gov.uk/Pages/planning/pdf/registers/developercontribution.csv","entry-date":"2024-01-10T00:21:57.170310","request-headers":{"Accept":"*/*","Accept-Encoding":"gzip, deflate","Connection":"keep-alive","User-Agent":"DLUHC Digital Land"},"response-headers":{"Accept-Ranges":"bytes","Cache-Control":"private,max-age=0","Content-Length":"718","Content-Type":"text/html","Date":"Wed, 10 Jan 2024 00:23:01 GMT","Expires":"Tue, 26 Dec 2023 00:23:06 GMT","MicrosoftSharePointTeamServices":"16.0.0.10349: 1; RequireReadOnly","Public-Extension":"http://schemas.microsoft.com/repl-2","SPIisLatency":"0","SPRequestDuration":"18","SPRequestGuid":"d32e00a1-c507-00bb-f78b-57bd2c3b9cc8","Server":"Microsoft-IIS/8.5","Strict-Transport-Security":"max-age=31536000","X-FRAME-OPTIONS":"SAMEORIGIN","X-Powered-By":"nosniff, ARR/3.0","X-SharePointHealthScore":"0","request-id":"d32e00a1-c507-00bb-f78b-57bd2c3b9cc8"},"ssl-verify":true,"status":"404"}