{"elapsed":"1.218","endpoint-url":"https://www.broxbourne.gov.uk/downloads/file/1305/developer-transactions","entry-date":"2023-04-25T00:21:04.627924","request-headers":{"Accept":"*/*","Accept-Encoding":"gzip, deflate","Connection":"keep-alive","Cookie":"PHPSESSID=FCh2P%2CZgb2Q1SQz23s8WqgQoSVbH9vxfsOwfyHqqOEvKTkIFXzfqT2oXiN9l63Xe","User-Agent":"DLUHC Digital Land"},"response-headers":{"Cache-Control":"max-age=0, must-revalidate, private","Connection":"keep-alive","Content-Type":"text/html; charset=UTF-8","Date":"Tue, 25 Apr 2023 00:22:45 GMT","Expires":"Tue, 25 Apr 2023 00:22:45 GMT","Server":"Web Server","Transfer-Encoding":"chunked","X-Content-Type-Options":"nosniff","X-Frame-Options":"SAMEORIGIN","X-XSS-Protection":"1; mode=block"},"ssl-verify":true,"status":"404"}