{"elapsed":"1.359","endpoint-url":"https://www.carlisle.gov.uk/Portals/24/Documents/Evidence_Base/IFS/developer-agreement-transactions20201230.csv","entry-date":"2023-05-07T00:20:15.221739","request-headers":{"Accept":"*/*","Accept-Encoding":"gzip, deflate","Connection":"keep-alive","User-Agent":"DLUHC Digital Land"},"resource":"1ac5852856bd9ed721caba9ed88a27ca6e65776f2ee82b7e717e6d348ad3f9a8","response-headers":{"Accept-Ranges":"bytes","CF-Cache-Status":"MISS","CF-RAY":"7c355790d8ef0a93-IAD","Cache-Control":"max-age=691200","Connection":"keep-alive","Content-Length":"2151","Content-Type":"application/octet-stream","Date":"Sun, 07 May 2023 00:28:18 GMT","NEL":"{\"success_fraction\":0,\"report_to\":\"cf-nel\",\"max_age\":604800}","Report-To":"{\"endpoints\":[{\"url\":\"https:\\/\\/a.nel.cloudflare.com\\/report\\/v3?s=3FtfMpLd%2Btxl%2F58EbnOtjFA8CxTAjxdREL6RtJmuD%2FSds%2Bu1mXISbCCUZ3wOBMvywGHEY%2BNQGktViaRnYsP2Jv9EeXk%2BGN7KMnVzxon43nmtLms8SudCtIUGZSh9kNnLY8yGKhw%3D\"}],\"group\":\"cf-nel\",\"max_age\":604800}","Server":"cloudflare","Vary":"Accept-Encoding","etag":"\"df75269030e8d61:0\"","last-modified":"Mon, 11 Jan 2021 15:43:52 GMT","strict-transport-security":"max-age=63072000","x-content-type-options":"nosniff","x-frame-options":"SAMEORIGIN","x-ua-compatible":"IE=edge","x-xss-protection":"1; mode=block"},"ssl-verify":true,"status":"200"}