{"elapsed":"1.269","endpoint-url":"https://www.southhams.gov.uk/developer-agreement-contribution","entry-date":"2023-10-29T00:21:16.001092","request-headers":{"Accept":"*/*","Accept-Encoding":"gzip, deflate","Connection":"keep-alive","User-Agent":"DLUHC Digital Land"},"resource":"dc54c8a3e945e684ff63739f222441de6e5a0069a3f24eb9632ebacb67b53ef1","response-headers":{"Accept-Ranges":"bytes","CF-Cache-Status":"MISS","CF-RAY":"81d7474b0f942abf-LAX","Cache-Control":"max-age=14400","Connection":"keep-alive","Content-Length":"16584","Content-Type":"application/vnd.openxmlformats-officedocument.spreadsheetml.sheet","Date":"Sun, 29 Oct 2023 00:24:57 GMT","ETag":"\"6479ddae-40c8\"","Last-Modified":"Fri, 02 Jun 2023 12:16:46 GMT","NEL":"{\"success_fraction\":0,\"report_to\":\"cf-nel\",\"max_age\":604800}","Report-To":"{\"endpoints\":[{\"url\":\"https:\\/\\/a.nel.cloudflare.com\\/report\\/v3?s=XmSR77T29%2FK83MUUhVEq0EEh6rAbTWTrdZ4zmfAao5MTQDTHeERzz2IDN%2BVaZL255X%2BIqCarI%2F6jfzz1stLHmZSfg%2FVRhtm%2BJxkAeV9KqdpGYR3b4PHDQNJcYMzPiwIV04AbQ4Bcvw%3D%3D\"}],\"group\":\"cf-nel\",\"max_age\":604800}","Server":"cloudflare","Vary":"Accept-Encoding","X-Content-Type-Options":"nosniff","alt-svc":"h3=\":443\"; ma=86400"},"ssl-verify":true,"status":"200"}