{"elapsed":"0.797","endpoint-url":"https://cdn-eastherts.onwebcurl.com/s3fs-public/2021-11/East%20Herts%20Council%20-%20CVS%20File%202%20-%20developer-agreement-contribution_2020-21.xlsx","entry-date":"2023-11-08T00:20:48.532083","request-headers":{"Accept":"*/*","Accept-Encoding":"gzip, deflate","Connection":"keep-alive","User-Agent":"DLUHC Digital Land"},"resource":"c12105e3f9ef0e78ab2e47038e2069d57be59bd2bb13822ee4f56acf9832102f","response-headers":{"Accept-Ranges":"bytes","Cache-Control":"max-age=3600","Content-Length":"19108","Content-Type":"application/vnd.openxmlformats-officedocument.spreadsheetml.sheet","Date":"Wed, 08 Nov 2023 00:24:29 GMT","Last-Modified":"Wed, 24 Nov 2021 21:31:08 GMT","Surrogate-Control":"max-age=3600;hw-h2proxy","X-HW":"1699403068.cdn4-pxy212-dfw02.da2.evs,1699403068.cds242.da2.p","etag":"\"246c7582d86f97494827e84bbded25ce\"","strict-transport-security":"max-age=15552000; includeSubDomains; preload","x-amz-request-id":"tx00000978e207c89b7807c-00654ad53c-bc9dee46-fra1b","x-envoy-upstream-healthchecked-cluster":"","x-rgw-object-type":"Normal"},"ssl-verify":true,"status":"200"}