{"elapsed":"0.435","endpoint-url":"https://www.eastcambs.gov.uk/sites/default/files/developer-agreement_2020-10-12_1.csv","entry-date":"2022-05-11T00:23:00.211768","request-headers":{"Accept":"*/*","Accept-Encoding":"gzip, deflate","Connection":"keep-alive","User-Agent":"DLUHC Digital Land"},"resource":"2c0e87f1e39d1a8f5622e82027787b4feef9eb5dd8dcbc11612b2f1bc3f5cd41","response-headers":{"Accept-Ranges":"bytes","Age":"0","Connection":"keep-alive","Content-Length":"19446","Content-Type":"text/csv","Date":"Wed, 11 May 2022 00:24:50 GMT","Etag":"\"626ad58a-4bf6\"","Last-Modified":"Thu, 28 Apr 2022 17:57:30 GMT","Server":"nginx","Strict-Transport-Security":"max-age=300","Traceparent":"00-fac4c487db734ceaaaf3f361d1aecc60-ec70d61e201c08cb-00","Via":"1.1 varnish, 1.1 varnish","X-Cache":"MISS, MISS","X-Cache-Hits":"0, 0","X-Cloud-Trace-Context":"fac4c487db734ceaaaf3f361d1aecc60/17037352815218657483;o=0","X-Pantheon-Styx-Hostname":"styx-fe3fe4-c-84b77b49bd-5cw4w","X-Served-By":"cache-ams21053-AMS, cache-iad-kiad7000176-IAD","X-Styx-Req-Id":"c58fc538-d0c0-11ec-8e04-aae31c67b632","X-Timer":"S1652228691.801017,VS0,VE104"},"ssl-verify":true,"status":"200"}