{"elapsed":"0.872","endpoint-url":"https://www.arun.gov.uk/developer-agreement-latest","entry-date":"2023-12-15T00:21:51.928203","request-headers":{"Accept":"*/*","Accept-Encoding":"gzip, deflate","Connection":"keep-alive","Cookie":"JSESSIONID=C130D13631E1712E66F149B5488DEAF3; TS01292376=0163a1acfb9ff1184faec0d8af659fbdcff03d6da2bc2161cc2eb3c4aa614fe0382c80b3ce09174a5c8a43d512cab26570ee07b4a9","User-Agent":"DLUHC Digital Land"},"resource":"c1334a890d50c78cd6e0dda9c5105761f10290d85fd0c91584e33e6bc378c06d","response-headers":{"Connection":"keep-alive","Content-Disposition":"inline; filename=developer-agreement_20230717.csv","Content-Length":"200217","Content-Type":"text/csv","Date":"Fri, 15 Dec 2023 00:23:30 GMT","Strict-Transport-Security":"max-age=31536000","X-Content-Type-Options":"nosniff","X-Frame-Options":"SAMEORIGIN","X-Responder":"RD2","X-XSS-Protection":"1; mode=block"},"ssl-verify":true,"status":"200"}