{"bytes":2279,"elapsed":"0.162","endpoint-url":"https://raw.githubusercontent.com/digital-land/developer-contributions-collection/main/data/contribution-purpose.csv","entry-date":"2021-09-17T01:05:52.888995","request-headers":{"Accept":"*/*","Accept-Encoding":"gzip, deflate","Connection":"keep-alive","User-Agent":"Digital Land"},"resource":"50ce3623172e4c8b8a900426d17614f9e7010145cb140c7a699b9fdd11a9cdd5","response-headers":{"Accept-Ranges":"bytes","Access-Control-Allow-Origin":"*","Cache-Control":"max-age=300","Connection":"keep-alive","Content-Encoding":"gzip","Content-Length":"541","Content-Security-Policy":"default-src 'none'; style-src 'unsafe-inline'; sandbox","Content-Type":"text/plain; charset=utf-8","Date":"Fri, 17 Sep 2021 01:05:53 GMT","ETag":"W/\"8b1d10caad8c73739ee74d7b7c766814fc89dd16fe65732b616f4b140e2d2f1c\"","Expires":"Fri, 17 Sep 2021 01:10:53 GMT","Source-Age":"0","Strict-Transport-Security":"max-age=31536000","Vary":"Authorization,Accept-Encoding,Origin","Via":"1.1 varnish","X-Cache":"MISS","X-Cache-Hits":"0","X-Content-Type-Options":"nosniff","X-Fastly-Request-ID":"db446ec8afdb51ba41a1aa0199da866421fa8c05","X-Frame-Options":"deny","X-GitHub-Request-Id":"5DAA:55A8:A55AE:10D977:6143E9F1","X-Served-By":"cache-sea4456-SEA","X-Timer":"S1631840754.743816,VS0,VE153","X-XSS-Protection":"1; mode=block"},"ssl-verify":true,"status":"200"}