{"elapsed":"0.738","endpoint-url":"https://www.dartmoor.gov.uk/__data/assets/file/0009/410112/developer-agreement-transaction_20211214.csv","entry-date":"2023-12-11T00:25:01.171786","request-headers":{"Accept":"*/*","Accept-Encoding":"gzip, deflate","Connection":"keep-alive","Cookie":"SQ_SYSTEM_SESSION=7645c7ff5d560d6bc83a84bfddd1d15e","User-Agent":"DLUHC Digital Land"},"response-headers":{"Cache-Control":"private, max-age=0","Connection":"keep-alive","Content-Encoding":"gzip","Content-Type":"text/html; charset=utf-8","Date":"Mon, 11 Dec 2023 00:27:55 GMT","Expires":"Mon, 11 Dec 2023 00:57:54 GMT","Pragma":"cache","Server":"openresty","Transfer-Encoding":"chunked","Vary":"Accept-Encoding, Accept-Encoding","Via":"1.1 np2-web01.ash2.squiz.cloud","X-Cache":"MISS from np2-web01.ash2.squiz.cloud","X-Content-Type-Options":"nosniff","X-Frame-Options":"SAMEORIGIN","X-Request-ID":"f6fcf78f-78ec-4f7d-89af-8f25ab6c5143","X-upgrade-enabled":"off"},"ssl-verify":true,"status":"404"}