{"elapsed":"0.419","endpoint-url":"https://cbccrmdata.blob.core.windows.net/noteattachment/CBC-Fees-and-charges-Developer-agreement-contributions-Developer%20Agreement%20Contributions_20201202.csv","entry-date":"2023-07-25T00:24:06.436125","request-headers":{"Accept":"*/*","Accept-Encoding":"gzip, deflate","Connection":"keep-alive","User-Agent":"DLUHC Digital Land"},"response-headers":{"Content-Length":"215","Content-Type":"application/xml","Date":"Tue, 25 Jul 2023 00:24:52 GMT","Server":"Windows-Azure-Blob/1.0 Microsoft-HTTPAPI/2.0","x-ms-request-id":"c97187d1-401e-002d-028e-be1b9c000000","x-ms-version":"2009-09-19"},"ssl-verify":true,"status":"404"}