{"elapsed":"1.058","endpoint-url":"https://www.arun.gov.uk/developer-agreement-latest","entry-date":"2024-02-04T00:22:10.881323","request-headers":{"Accept":"*/*","Accept-Encoding":"gzip, deflate","Connection":"keep-alive","Cookie":"JSESSIONID=94D6C1DA3EF1224DE5667B27064F3E72; TS01292376=0188c5268e649cb87cbbae24ef9c7859c0cd0ecc34076a8919c9f681c4757c09f4e99bc8edb0e429bf4a4e48fb24f98f4c0802400c","User-Agent":"DLUHC Digital Land"},"resource":"c1334a890d50c78cd6e0dda9c5105761f10290d85fd0c91584e33e6bc378c06d","response-headers":{"Connection":"keep-alive","Content-Disposition":"inline; filename=developer-agreement_20230717.csv","Content-Length":"200217","Content-Type":"text/csv","Date":"Sun, 04 Feb 2024 00:23:48 GMT","Strict-Transport-Security":"max-age=31536000","X-Content-Type-Options":"nosniff","X-Frame-Options":"SAMEORIGIN","X-Responder":"RD3","X-XSS-Protection":"1; mode=block"},"ssl-verify":true,"status":"200"}