{"elapsed":"1.285","endpoint-url":"https://southhams.gov.uk/developer-agreement","entry-date":"2024-01-20T00:20:48.072135","request-headers":{"Accept":"*/*","Accept-Encoding":"gzip, deflate","Connection":"keep-alive","User-Agent":"DLUHC Digital Land"},"resource":"f88ceb8f27b0e3f7d1f65ca120626381aef3d60f757575c04fc45740a2be0d56","response-headers":{"Accept-Ranges":"bytes","Connection":"keep-alive","Content-Length":"4401","Content-Type":"application/octet-stream","Date":"Sat, 20 Jan 2024 00:21:11 GMT","ETag":"\"6584403b-1131\"","Last-Modified":"Thu, 21 Dec 2023 13:40:11 GMT","Server":"nginx","Via":"1.1 b9fa5c33e059fb3ed603bd8fcb9d4aea.cloudfront.net (CloudFront)","X-Amz-Cf-Id":"FgWU0kThq_pMyjKT0r-GVKr99mH_CR6xLGK3RezONhI95s-1acFVzQ==","X-Amz-Cf-Pop":"JFK50-P1","X-Cache":"Miss from cloudfront","X-Content-Type-Options":"nosniff"},"ssl-verify":true,"status":"200"}